{
    "marketHealthy": true,
    "signals": [
        {
            "ticker": "AEE",
            "score": 100,
            "pattern": "Conservative VCP",
            "currentPrice": 104.18,
            "buyAt": 104.87,
            "goal": 107.21,
            "stopLoss": 101.92,
            "rsi": 62.43
        },
        {
            "ticker": "CME",
            "score": 100,
            "pattern": "Conservative VCP",
            "currentPrice": 285.44,
            "buyAt": 286.76,
            "goal": 295.41,
            "stopLoss": 277.96,
            "rsi": 64.65
        },
        {
            "ticker": "CNP",
            "score": 100,
            "pattern": "Conservative VCP",
            "currentPrice": 39.85,
            "buyAt": 40.0,
            "goal": 41.04,
            "stopLoss": 38.95,
            "rsi": 61.8
        },
        {
            "ticker": "EIX",
            "score": 100,
            "pattern": "Conservative VCP",
            "currentPrice": 62.57,
            "buyAt": 63.19,
            "goal": 65.11,
            "stopLoss": 60.67,
            "rsi": 62.96
        },
        {
            "ticker": "MSCI",
            "score": 100,
            "pattern": "Conservative VCP",
            "currentPrice": 612.16,
            "buyAt": 613.34,
            "goal": 639.74,
            "stopLoss": 591.47,
            "rsi": 64.63
        },
        {
            "ticker": "DAY",
            "score": 80,
            "pattern": "Conservative VCP",
            "currentPrice": 69.33,
            "buyAt": 69.65,
            "goal": 69.68,
            "stopLoss": 69.08,
            "rsi": 54.49
        },
        {
            "ticker": "ETR",
            "score": 80,
            "pattern": "Conservative VCP",
            "currentPrice": 97.24,
            "buyAt": 97.72,
            "goal": 100.59,
            "stopLoss": 94.73,
            "rsi": 61.18
        },
        {
            "ticker": "HOLX",
            "score": 80,
            "pattern": "Conservative VCP",
            "currentPrice": 75.14,
            "buyAt": 75.36,
            "goal": 75.63,
            "stopLoss": 74.78,
            "rsi": 60.56
        },
        {
            "ticker": "PPL",
            "score": 80,
            "pattern": "Conservative VCP",
            "currentPrice": 36.97,
            "buyAt": 37.21,
            "goal": 38.12,
            "stopLoss": 36.11,
            "rsi": 64.95
        }
    ],
    "lastUpdated": "2026-01-28 17:29:45"
}