{
    "marketHealthy": true,
    "signals": [
        {
            "ticker": "F",
            "score": 100,
            "pattern": "Conservative VCP",
            "currentPrice": 14.31,
            "buyAt": 14.34,
            "goal": 14.99,
            "stopLoss": 13.79,
            "rsi": 60.46
        },
        {
            "ticker": "HII",
            "score": 100,
            "pattern": "Conservative VCP",
            "currentPrice": 446.06,
            "buyAt": 449.03,
            "goal": 479.42,
            "stopLoss": 421.04,
            "rsi": 64.18
        },
        {
            "ticker": "NVDA",
            "score": 100,
            "pattern": "Conservative VCP",
            "currentPrice": 193.21,
            "buyAt": 194.49,
            "goal": 205.14,
            "stopLoss": 184.27,
            "rsi": 58.54
        },
        {
            "ticker": "PPL",
            "score": 100,
            "pattern": "Conservative VCP",
            "currentPrice": 37.83,
            "buyAt": 38.14,
            "goal": 39.34,
            "stopLoss": 36.71,
            "rsi": 63.48
        }
    ],
    "lastUpdated": "2026-02-24 17:57:57"
}